[
  {
    "sessionTitle": "Introduction to Python",
    "tutorName": "Alice Johnson",
    "tutorEmail": "alice.johnson@example.com",
    "desc": "Learn the basics of Python programming.",
    "registrationStart": "2024-06-01T09:00:00Z",
    "registrationEnd": "2024-06-15T17:00:00Z",
    "classStart": "2024-07-01T10:00:00Z",
    "classEnd": "2024-07-01T12:00:00Z",
    "duration": "2 hours",
    "fee": 20,
    "additionalInfo": "No prior experience required."
  },
  {
    "sessionTitle": "Advanced JavaScript",
    "tutorName": "Bob Smith",
    "tutorEmail": "bob.smith@example.com",
    "desc": "Deep dive into advanced concepts in JavaScript.",
    "registrationStart": "2024-06-05T09:00:00Z",
    "registrationEnd": "2024-06-25T17:00:00Z",
    "classStart": "2024-07-10T14:00:00Z",
    "classEnd": "2024-07-10T16:00:00Z",
    "duration": "2 hours",
    "fee": 30,
    "additionalInfo": "Basic knowledge of JavaScript required."
  },
  {
    "sessionTitle": "Data Science with Python",
    "tutorName": "Charlie Lee",
    "tutorEmail": "charlie.lee@example.com",
    "desc": "Introduction to data science using Python.",
    "registrationStart": "2024-06-10T09:00:00Z",
    "registrationEnd": "2024-06-30T17:00:00Z",
    "classStart": "2024-07-15T10:00:00Z",
    "classEnd": "2024-07-15T13:00:00Z",
    "duration": "3 hours",
    "fee": 25,
    "additionalInfo": "Basic Python knowledge required."
  },
  {
    "sessionTitle": "Web Development Bootcamp",
    "tutorName": "Dana White",
    "tutorEmail": "dana.white@example.com",
    "desc": "Learn full-stack web development from scratch.",
    "registrationStart": "2024-06-15T09:00:00Z",
    "registrationEnd": "2024-07-01T17:00:00Z",
    "classStart": "2024-07-20T09:00:00Z",
    "classEnd": "2024-07-20T17:00:00Z",
    "duration": "8 hours",
    "fee": 50,
    "additionalInfo": "Lunch will be provided."
  },
  {
    "sessionTitle": "Machine Learning Basics",
    "tutorName": "Eva Brown",
    "tutorEmail": "eva.brown@example.com",
    "desc": "Understand the basics of machine learning.",
    "registrationStart": "2024-06-20T09:00:00Z",
    "registrationEnd": "2024-07-10T17:00:00Z",
    "classStart": "2024-07-25T10:00:00Z",
    "classEnd": "2024-07-25T12:00:00Z",
    "duration": "2 hours",
    "fee": 30,
    "additionalInfo": "Familiarity with Python is recommended."
  },
  {
    "sessionTitle": "Introduction to HTML & CSS",
    "tutorName": "Frank Miller",
    "tutorEmail": "frank.miller@example.com",
    "desc": "Learn how to create websites using HTML and CSS.",
    "registrationStart": "2024-06-25T09:00:00Z",
    "registrationEnd": "2024-07-15T17:00:00Z",
    "classStart": "2024-07-30T10:00:00Z",
    "classEnd": "2024-07-30T13:00:00Z",
    "duration": "3 hours",
    "fee": 20,
    "additionalInfo": "Bring your own laptop."
  },
  {
    "sessionTitle": "Free Coding Workshop",
    "tutorName": "Alice Johnson",
    "tutorEmail": "alice.johnson@example.com",
    "desc": "A free workshop for beginners to get started with coding.",
    "registrationStart": "2024-06-05T09:00:00Z",
    "registrationEnd": "2024-06-20T17:00:00Z",
    "classStart": "2024-07-05T10:00:00Z",
    "classEnd": "2024-07-05T12:00:00Z",
    "duration": "2 hours",
    "fee": 0,
    "additionalInfo": "No experience required."
  },
  {
    "sessionTitle": "Intro to Cloud Computing",
    "tutorName": "Bob Smith",
    "tutorEmail": "bob.smith@example.com",
    "desc": "Learn the basics of cloud computing and its applications.",
    "registrationStart": "2024-06-08T09:00:00Z",
    "registrationEnd": "2024-06-28T17:00:00Z",
    "classStart": "2024-07-08T10:00:00Z",
    "classEnd": "2024-07-08T12:00:00Z",
    "duration": "2 hours",
    "fee": 25,
    "additionalInfo": "Basic IT knowledge recommended."
  },
  {
    "sessionTitle": "Deep Learning with TensorFlow",
    "tutorName": "Charlie Lee",
    "tutorEmail": "charlie.lee@example.com",
    "desc": "Explore deep learning techniques using TensorFlow.",
    "registrationStart": "2024-06-12T09:00:00Z",
    "registrationEnd": "2024-07-02T17:00:00Z",
    "classStart": "2024-07-12T14:00:00Z",
    "classEnd": "2024-07-12T17:00:00Z",
    "duration": "3 hours",
    "fee": 40,
    "additionalInfo": "Prior knowledge of machine learning is required."
  },
  {
    "sessionTitle": "Full Stack Development",
    "tutorName": "Dana White",
    "tutorEmail": "dana.white@example.com",
    "desc": "Master the skills needed for full-stack development.",
    "registrationStart": "2024-06-18T09:00:00Z",
    "registrationEnd": "2024-07-05T17:00:00Z",
    "classStart": "2024-07-18T09:00:00Z",
    "classEnd": "2024-07-18T17:00:00Z",
    "duration": "8 hours",
    "fee": 60,
    "additionalInfo": "Lunch and refreshments will be provided."
  },
  {
    "sessionTitle": "Intro to Cybersecurity",
    "tutorName": "Eva Brown",
    "tutorEmail": "eva.brown@example.com",
    "desc": "Learn the fundamentals of cybersecurity.",
    "registrationStart": "2024-06-22T09:00:00Z",
    "registrationEnd": "2024-07-12T17:00:00Z",
    "classStart": "2024-07-22T10:00:00Z",
    "classEnd": "2024-07-22T12:00:00Z",
    "duration": "2 hours",
    "fee": 30,
    "additionalInfo": "Basic computer knowledge required."
  },
  {
    "sessionTitle": "Web Design Fundamentals",
    "tutorName": "Frank Miller",
    "tutorEmail": "frank.miller@example.com",
    "desc": "Learn the principles of web design and user experience.",
    "registrationStart": "2024-06-25T09:00:00Z",
    "registrationEnd": "2024-07-15T17:00:00Z",
    "classStart": "2024-07-25T14:00:00Z",
    "classEnd": "2024-07-25T17:00:00Z",
    "duration": "3 hours",
    "fee": 25,
    "additionalInfo": "Bring your own laptop."
  },
  {
    "sessionTitle": "Free Python Coding Bootcamp",
    "tutorName": "Alice Johnson",
    "tutorEmail": "alice.johnson@example.com",
    "desc": "A free bootcamp for beginners to learn Python.",
    "registrationStart": "2024-06-07T09:00:00Z",
    "registrationEnd": "2024-06-21T17:00:00Z",
    "classStart": "2024-07-07T09:00:00Z",
    "classEnd": "2024-07-07T17:00:00Z",
    "duration": "8 hours",
    "fee": 0,
    "additionalInfo": "Lunch will be provided."
  },
  {
    "sessionTitle": "Java for Beginners",
    "tutorName": "Bob Smith",
    "tutorEmail": "bob.smith@example.com",
    "desc": "Learn the basics of Java programming.",
    "registrationStart": "2024-06-10T09:00:00Z",
    "registrationEnd": "2024-06-30T17:00:00Z",
    "classStart": "2024-07-10T10:00:00Z",
    "classEnd": "2024-07-10T12:00:00Z",
    "duration": "2 hours",
    "fee": 20,
    "additionalInfo": "No prior experience required."
  },
  {
    "sessionTitle": "Intermediate SQL",
    "tutorName": "Charlie Lee",
    "tutorEmail": "charlie.lee@example.com",
    "desc": "Build on your SQL skills with this intermediate course.",
    "registrationStart": "2024-06-14T09:00:00Z",
    "registrationEnd": "2024-07-04T17:00:00Z",
    "classStart": "2024-07-14T14:00:00Z",
    "classEnd": "2024-07-14T16:00:00Z",
    "duration": "2 hours",
    "fee": 30,
    "additionalInfo": "Basic SQL knowledge required."
  },
  {
    "sessionTitle": "React.js Essentials",
    "tutorName": "Dana White",
    "tutorEmail": "dana.white@example.com",
    "desc": "Learn the essentials of React.js for building dynamic web applications.",
    "registrationStart": "2024-06-17T09:00:00Z",
    "registrationEnd": "2024-07-07T17:00:00Z",
    "classStart": "2024-07-17T10:00:00Z",
    "classEnd": "2024-07-17T13:00:00Z",
    "duration": "3 hours",
    "fee": 35,
    "additionalInfo": "Basic JavaScript knowledge required."
  },
  {
    "sessionTitle": "Intro to Artificial Intelligence",
    "tutorName": "Eva Brown",
    "tutorEmail": "eva.brown@example.com",
    "desc": "Discover the basics of artificial intelligence and its applications.",
    "registrationStart": "2024-06-21T09:00:00Z",
    "registrationEnd": "2024-07-11T17:00:00Z",
    "classStart": "2024-07-21T10:00:00Z",
    "classEnd": "2024-07-21T12:00:00Z",
    "duration": "2 hours",
    "fee": 30,
    "additionalInfo": "Basic knowledge of programming recommended."
  },
  {
    "sessionTitle": "Introduction to PHP",
    "tutorName": "Frank Miller",
    "tutorEmail": "frank.miller@example.com",
    "desc": "Learn the basics of PHP programming.",
    "registrationStart": "2024-06-25T09:00:00Z",
    "registrationEnd": "2024-07-15T17:00:00Z",
    "classStart": "2024-07-25T10:00:00Z",
    "classEnd": "2024-07-25T12:00:00Z",
    "duration": "2 hours",
    "fee": 20,
    "additionalInfo": "Bring your own laptop."
  },
  {
    "sessionTitle": "Free Web Development Workshop",
    "tutorName": "Alice Johnson",
    "tutorEmail": "alice.johnson@example.com",
    "desc": "A free workshop for beginners to learn web development.",
    "registrationStart": "2024-06-05T09:00:00Z",
    "registrationEnd": "2024-06-20T17:00:00Z",
    "classStart": "2024-07-05T10:00:00Z",
    "classEnd": "2024-07-05T12:00:00Z",
    "duration": "2 hours",
    "fee": 0,
    "additionalInfo": "No experience required."
  },
  {
    "sessionTitle": "C++ Programming Basics",
    "tutorName": "Bob Smith",
    "tutorEmail": "bob.smith@example.com",
    "desc": "Learn the basics of C++ programming.",
    "registrationStart": "2024-06-10T09:00:00Z",
    "registrationEnd": "2024-06-30T17:00:00Z",
    "classStart": "2024-07-10T10:00:00Z",
    "classEnd": "2024-07-10T12:00:00Z",
    "duration": "2 hours",
    "fee": 25,
    "additionalInfo": "No prior experience required."
  },
  {
    "sessionTitle": "Big Data Analytics",
    "tutorName": "Charlie Lee",
    "tutorEmail": "charlie.lee@example.com",
    "desc": "Explore big data analytics techniques and tools.",
    "registrationStart": "2024-06-14T09:00:00Z",
    "registrationEnd": "2024-07-04T17:00:00Z",
    "classStart": "2024-07-14T14:00:00Z",
    "classEnd": "2024-07-14T17:00:00Z",
    "duration": "3 hours",
    "fee": 35,
    "additionalInfo": "Basic knowledge of data analysis recommended."
  },
  {
    "sessionTitle": "Node.js for Beginners",
    "tutorName": "Dana White",
    "tutorEmail": "dana.white@example.com",
    "desc": "Learn the basics of Node.js for backend development.",
    "registrationStart": "2024-06-18T09:00:00Z",
    "registrationEnd": "2024-07-05T17:00:00Z",
    "classStart": "2024-07-18T10:00:00Z",
    "classEnd": "2024-07-18T12:00:00Z",
    "duration": "2 hours",
    "fee": 25,
    "additionalInfo": "Basic JavaScript knowledge required."
  },
  {
    "sessionTitle": "Introduction to Django",
    "tutorName": "Eva Brown",
    "tutorEmail": "eva.brown@example.com",
    "desc": "Learn the fundamentals of web development with Django.",
    "registrationStart": "2024-06-22T09:00:00Z",
    "registrationEnd": "2024-07-12T17:00:00Z",
    "classStart": "2024-07-22T10:00:00Z",
    "classEnd": "2024-07-22T12:00:00Z",
    "duration": "2 hours",
    "fee": 30,
    "additionalInfo": "Basic Python knowledge required."
  },
  {
    "sessionTitle": "Free JavaScript Basics",
    "tutorName": "Frank Miller",
    "tutorEmail": "frank.miller@example.com",
    "desc": "A free session to learn the basics of JavaScript.",
    "registrationStart": "2024-06-05T09:00:00Z",
    "registrationEnd": "2024-06-20T17:00:00Z",
    "classStart": "2024-07-05T10:00:00Z",
    "classEnd": "2024-07-05T12:00:00Z",
    "duration": "2 hours",
    "fee": 0,
    "additionalInfo": "No prior experience required."
  },
  {
    "sessionTitle": "Mobile App Development with Flutter",
    "tutorName": "Alice Johnson",
    "tutorEmail": "alice.johnson@example.com",
    "desc": "Learn how to develop mobile applications using Flutter.",
    "registrationStart": "2024-06-07T09:00:00Z",
    "registrationEnd": "2024-06-21T17:00:00Z",
    "classStart": "2024-07-07T09:00:00Z",
    "classEnd": "2024-07-07T13:00:00Z",
    "duration": "4 hours",
    "fee": 30,
    "additionalInfo": "Basic programming knowledge recommended."
  },
  {
    "sessionTitle": "Free Data Science Intro",
    "tutorName": "Bob Smith",
    "tutorEmail": "bob.smith@example.com",
    "desc": "A free session to introduce the basics of data science.",
    "registrationStart": "2024-06-10T09:00:00Z",
    "registrationEnd": "2024-06-30T17:00:00Z",
    "classStart": "2024-07-10T10:00:00Z",
    "classEnd": "2024-07-10T12:00:00Z",
    "duration": "2 hours",
    "fee": 0,
    "additionalInfo": "Basic Python knowledge recommended."
  },
  {
    "sessionTitle": "Cloud Computing with AWS",
    "tutorName": "Charlie Lee",
    "tutorEmail": "charlie.lee@example.com",
    "desc": "Learn the basics of cloud computing with AWS.",
    "registrationStart": "2024-06-12T09:00:00Z",
    "registrationEnd": "2024-07-02T17:00:00Z",
    "classStart": "2024-07-12T10:00:00Z",
    "classEnd": "2024-07-12T13:00:00Z",
    "duration": "3 hours",
    "fee": 35,
    "additionalInfo": "Basic IT knowledge recommended."
  },
  {
    "sessionTitle": "Web Application Security",
    "tutorName": "Dana White",
    "tutorEmail": "dana.white@example.com",
    "desc": "Learn how to secure web applications.",
    "registrationStart": "2024-06-18T09:00:00Z",
    "registrationEnd": "2024-07-05T17:00:00Z",
    "classStart": "2024-07-18T14:00:00Z",
    "classEnd": "2024-07-18T17:00:00Z",
    "duration": "3 hours",
    "fee": 40,
    "additionalInfo": "Basic web development knowledge required."
  },
  {
    "sessionTitle": "Intro to Blockchain",
    "tutorName": "Eva Brown",
    "tutorEmail": "eva.brown@example.com",
    "desc": "Understand the basics of blockchain technology.",
    "registrationStart": "2024-06-21T09:00:00Z",
    "registrationEnd": "2024-07-11T17:00:00Z",
    "classStart": "2024-07-21T10:00:00Z",
    "classEnd": "2024-07-21T12:00:00Z",
    "duration": "2 hours",
    "fee": 30,
    "additionalInfo": "Basic IT knowledge recommended."
  },
  {
    "sessionTitle": "Angular Essentials",
    "tutorName": "Frank Miller",
    "tutorEmail": "frank.miller@example.com",
    "desc": "Learn the essentials of Angular for building dynamic web applications.",
    "registrationStart": "2024-06-25T09:00:00Z",
    "registrationEnd": "2024-07-15T17:00:00Z",
    "classStart": "2024-07-25T14:00:00Z",
    "classEnd": "2024-07-25T17:00:00Z",
    "duration": "3 hours",
    "fee": 35,
    "additionalInfo": "Basic JavaScript knowledge required."
  },
  {
    "sessionTitle": "Advanced Python Programming",
    "tutorName": "Alice Johnson",
    "tutorEmail": "alice.johnson@example.com",
    "desc": "Deep dive into advanced Python programming concepts.",
    "registrationStart": "2024-06-07T09:00:00Z",
    "registrationEnd": "2024-06-21T17:00:00Z",
    "classStart": "2024-07-07T14:00:00Z",
    "classEnd": "2024-07-07T17:00:00Z",
    "duration": "3 hours",
    "fee": 40,
    "additionalInfo": "Basic Python knowledge required."
  }
]
